latestearthquake/__init__.py
latestearthquake/latest_earthquake.py
livelatestearthquake_indonesia-0.0.8.dist-info/METADATA
livelatestearthquake_indonesia-0.0.8.dist-info/WHEEL
livelatestearthquake_indonesia-0.0.8.dist-info/licenses/LICENSE
livelatestearthquake_indonesia-0.0.8.dist-info/RECORD
