Metadata-Version: 2.1
Name: livelatestearthquake-indonesia
Version: 0.0.8
Summary: This package will get the live latest earthquake from BMKG | Meteorological, Climatological, and Geophysical Agency
Author-email: MDKovalesky <dzikrikovalesky@gmail.com>
License-File: LICENSE
Classifier: Development Status :: 5 - Production/Stable
Classifier: License :: OSI Approved :: GNU General Public License v3 or later (GPLv3+)
Classifier: Operating System :: OS Independent
Classifier: Programming Language :: Python :: 3
Requires-Python: >=3.7
